odoo8_addon_account_move_line_search_extension-8.0.1.0.0-py2.7-nspkg.pth
odoo8_addon_account_move_line_search_extension-8.0.1.0.0.dist-info/DESCRIPTION.rst
odoo8_addon_account_move_line_search_extension-8.0.1.0.0.dist-info/METADATA
odoo8_addon_account_move_line_search_extension-8.0.1.0.0.dist-info/RECORD
odoo8_addon_account_move_line_search_extension-8.0.1.0.0.dist-info/WHEEL
odoo8_addon_account_move_line_search_extension-8.0.1.0.0.dist-info/metadata.json
odoo8_addon_account_move_line_search_extension-8.0.1.0.0.dist-info/namespace_packages.txt
odoo8_addon_account_move_line_search_extension-8.0.1.0.0.dist-info/top_level.txt
odoo_addons/account_move_line_search_extension/README.rst
odoo_addons/account_move_line_search_extension/__init__.py
odoo_addons/account_move_line_search_extension/__openerp__.py
odoo_addons/account_move_line_search_extension/i18n/am.po
odoo_addons/account_move_line_search_extension/i18n/ar.po
odoo_addons/account_move_line_search_extension/i18n/bg.po
odoo_addons/account_move_line_search_extension/i18n/bs.po
odoo_addons/account_move_line_search_extension/i18n/ca.po
odoo_addons/account_move_line_search_extension/i18n/cs.po
odoo_addons/account_move_line_search_extension/i18n/da.po
odoo_addons/account_move_line_search_extension/i18n/de.po
odoo_addons/account_move_line_search_extension/i18n/el_GR.po
odoo_addons/account_move_line_search_extension/i18n/en_GB.po
odoo_addons/account_move_line_search_extension/i18n/es.po
odoo_addons/account_move_line_search_extension/i18n/es_CR.po
odoo_addons/account_move_line_search_extension/i18n/es_EC.po
odoo_addons/account_move_line_search_extension/i18n/es_MX.po
odoo_addons/account_move_line_search_extension/i18n/es_VE.po
odoo_addons/account_move_line_search_extension/i18n/et.po
odoo_addons/account_move_line_search_extension/i18n/eu.po
odoo_addons/account_move_line_search_extension/i18n/fi.po
odoo_addons/account_move_line_search_extension/i18n/fr.po
odoo_addons/account_move_line_search_extension/i18n/fr_CA.po
odoo_addons/account_move_line_search_extension/i18n/fr_CH.po
odoo_addons/account_move_line_search_extension/i18n/gl.po
odoo_addons/account_move_line_search_extension/i18n/hr.po
odoo_addons/account_move_line_search_extension/i18n/hr_HR.po
odoo_addons/account_move_line_search_extension/i18n/hu.po
odoo_addons/account_move_line_search_extension/i18n/it.po
odoo_addons/account_move_line_search_extension/i18n/ja.po
odoo_addons/account_move_line_search_extension/i18n/lt.po
odoo_addons/account_move_line_search_extension/i18n/lv.po
